Cosmic/__init__.py
Cosmic/cosmiclogger.py
skidx-0.1.3.dist-info/METADATA
skidx-0.1.3.dist-info/WHEEL
skidx-0.1.3.dist-info/top_level.txt
skidx-0.1.3.dist-info/RECORD
